tableschema_to_template/__init__.py
tableschema_to_template/create_xlsx.py
tableschema_to_template/errors.py
tableschema_to_template/ts2xl.py
tableschema_to_template/validate_schema.py
tableschema_to_template/validation_factory.py
tableschema_to_template-0.0.13.data/scripts/ts2xl.py
tableschema_to_template-0.0.13.dist-info/LICENSE
tableschema_to_template-0.0.13.dist-info/METADATA
tableschema_to_template-0.0.13.dist-info/WHEEL
tableschema_to_template-0.0.13.dist-info/top_level.txt
tableschema_to_template-0.0.13.dist-info/RECORD
