Metadata-Version: 2.1
Name: tableschema-to-template
Version: 0.0.13
Summary: Given a Frictionless Table Schema, generates an Excel template with input validation
Home-page: https://github.com/hubmapconsortium/tableschema-to-template
Author: Chuck McCallum
Author-email: mccallucc+tableschema@gmail.com
Classifier: Programming Language :: Python :: 3
Classifier: License :: OSI Approved :: MIT License
Classifier: Operating System :: OS Independent
Requires-Python: >=3.6
License-File: LICENSE
Requires-Dist: jsonschema (>=1.0.0)
Requires-Dist: pyyaml (>=3.13)
Requires-Dist: xlsxwriter (>=1.2.8)
